ar_corrector/__init__.py
ar_corrector/corrector.py
ar_corrector/dataset_creator.py
ar_corrector/io_handler.py
ar_corrector/preprocess.py
ar_corrector/proj_config.py
ar_corrector/string_manipulator.py
ar_corrector/models/__init__.py
ar_corrector/models/base_model.py
ar_corrector/models/markov_model.py
ar_corrector/models/n_gram.py
ar_corrector/models/vocabs_creator.py
ar_corrector/resources/close_vocabs.pickle
ar_corrector/resources/ngram.pickle
ar_corrector/resources/ngram_plus1.pickle
ar_corrector/resources/vocab_freqs.pickle
ar_corrector-1.1.6.dist-info/LICENSE.txt
ar_corrector-1.1.6.dist-info/METADATA
ar_corrector-1.1.6.dist-info/WHEEL
ar_corrector-1.1.6.dist-info/top_level.txt
ar_corrector-1.1.6.dist-info/RECORD
