Metadata-Version: 2.1
Name: ar-corrector
Version: 1.1.6
Summary: Arabic Spelling Correction
Home-page: UNKNOWN
Author: Bassel Kassem
Author-email: bassel.kassem.job@gmail.com
License: UNKNOWN
Download-URL: https://github.com/basselkassem/ar_corrector/archive/refs/tags/v1.1.6
Project-URL: Bug Reports, https://github.com/basselkassem/ar_corrector/issues
Project-URL: Funding, https://donate.pypi.org
Project-URL: Say Thanks!, https://github.com/basselkassem
Project-URL: Source, https://github.com/basselkassem/ar_corrector
Keywords: NLP,Spellingcheck
Platform: UNKNOWN
Classifier: Development Status :: 5 - Production/Stable
Classifier: Intended Audience :: Developers
Classifier: Topic :: Software Development :: Build Tools
Classifier: License :: OSI Approved :: MIT License
Classifier: Programming Language :: Python :: 3
Classifier: Programming Language :: Python :: 3.4
Classifier: Programming Language :: Python :: 3.5
Classifier: Programming Language :: Python :: 3.6
Requires-Python: >=3.6, <4
Requires-Dist: requests
